pylintfileheader/ThirdPartyNotices.txt
pylintfileheader/__init__.py
pylintfileheader/file_header_checker.py
pylintfileheader/plugin.py
pylintfileheader-1.0.0.dist-info/LICENSE.txt
pylintfileheader-1.0.0.dist-info/METADATA
pylintfileheader-1.0.0.dist-info/WHEEL
pylintfileheader-1.0.0.dist-info/top_level.txt
pylintfileheader-1.0.0.dist-info/RECORD
