Metadata-Version: 2.1
Name: pylintfileheader
Version: 1.0.0
Summary: Enables pylint to force a consistent file header.
Author: Leo Hanisch
License: MIT
Project-URL: Source, https://github.com/HaaLeo/pylint-file-header
Project-URL: Issue Tracker, https://github.com/HaaLeo/pylint-file-header/issues
Project-URL: Changelog, https://github.com/HaaLeo/pylint-file-header/blob/master/CHANGELOG.md#changelog
Project-URL: Funding, https://github.com/sponsors/HaaLeo
Keywords: pylintfileheader,pylint,file,module,header
Classifier: Development Status :: 5 - Production/Stable
Classifier: Intended Audience :: Developers
Classifier: License :: OSI Approved :: MIT License
Classifier: Operating System :: OS Independent
Classifier: Programming Language :: Python :: 3 :: Only
Classifier: Programming Language :: Python :: 3.8
Classifier: Programming Language :: Python :: 3.9
Classifier: Programming Language :: Python :: 3.10
Classifier: Programming Language :: Python :: 3.11
Classifier: Programming Language :: Python :: 3.12
Requires-Python: >=3.8
License-File: LICENSE.txt
Requires-Dist: pylint <4.0,>=3.0
